setup.py
uhcx/__init__.py
uhcx/exception.py
uhcx.egg-info/PKG-INFO
uhcx.egg-info/SOURCES.txt
uhcx.egg-info/dependency_links.txt
uhcx.egg-info/requires.txt
uhcx.egg-info/top_level.txt
uhcx/test/__init__.py