Metadata-Version: 1.1
Name: uhcx
Version: 0.2.1
Summary: Library for the uh.cx link shortener.
Home-page: http://uh.cx/
Author: J. Boehm
Author-email: jb@uh.cx
License: MIT
Platform: UNKNOWN
Classifier: Development Status :: 4 - Beta
Classifier: Intended Audience :: Developers
Classifier: Topic :: Internet :: WWW/HTTP
Classifier: License :: OSI Approved :: MIT License
Classifier: Programming Language :: Python :: 3
Classifier: Programming Language :: Python :: 3.2
Classifier: Programming Language :: Python :: 3.3
Classifier: Programming Language :: Python :: 3.4
